fastuav/__init__.py
fastuav/configurations/__init__.py
fastuav/configurations/doe_optimization_problem.yaml
fastuav/configurations/doe_simple_model.yaml
fastuav/configurations/doe_sobol_analysis.yaml
fastuav/configurations/fixedwing_mdo.yaml
fastuav/configurations/fixedwing_model.yaml
fastuav/configurations/hybrid_mdo.yaml
fastuav/configurations/hybrid_model.yaml
fastuav/configurations/missions_multirotor_lca.yaml
fastuav/configurations/multirotor_mda.yaml
fastuav/configurations/multirotor_mda_cots.yaml
fastuav/configurations/multirotor_mdo.yaml
fastuav/configurations/multirotor_mdo_cots.yaml
fastuav/configurations/multirotor_model.yaml
fastuav/configurations/multirotor_model_cots.yaml
fastuav/configurations/multirotor_performance.yaml
fastuav/constants.py
fastuav/data/__init__.py
fastuav/data/catalogues/Batteries/Non-Dominated-Augmented-Batteries.csv
fastuav/data/catalogues/ESC/ESC_data.csv
fastuav/data/catalogues/ESC/Non-Dominated-ESC.csv
fastuav/data/catalogues/Motors/Motors_Data.csv
fastuav/data/catalogues/Motors/Non-Dominated-Motors.csv
fastuav/data/catalogues/Propeller/.ipynb_checkpoints/APC_propellers_MR-checkpoint.csv
fastuav/data/catalogues/Propeller/APC_propellers.csv
fastuav/data/catalogues/Propeller/APC_propellers_for_uncertainty.csv
fastuav/data/catalogues/Propeller/APC_propellers_MR.csv
fastuav/data/catalogues/Propeller/APC_propellers_MR_old.csv
fastuav/data/catalogues/Propeller/performances/Non-Dominated-Propeller.csv
fastuav/data/catalogues/Propeller/performances/Propeller_Data.csv
fastuav/missions/missions_fixedwing.yaml
fastuav/missions/missions_hybrid.yaml
fastuav/missions/missions_multirotor.yaml
fastuav/missions/missions_multirotor_doe.yaml
fastuav/missions/missions_multirotor_off_design.yaml
fastuav/models/__init__.py
fastuav/models/add_ons/__init__.py
fastuav/models/add_ons/sample_discipline.py
fastuav/models/aerodynamics/__init__.py
fastuav/models/aerodynamics/aerodynamics_fixedwing.py
fastuav/models/aerodynamics/aerodynamics_hybrid.py
fastuav-0.1.1.dist-info/entry_points.txt
fastuav-0.1.1.dist-info/METADATA
fastuav-0.1.1.dist-info/WHEEL
fastuav-0.1.1.dist-info/RECORD
