Metadata-Version: 2.1
Name: fastuav
Version: 0.1.1
Summary: FAST-UAV is a framework for performing rapid Overall Aircraft Design for Unmanned Aerial Vehicles
Home-page: https://github.com/SizingLab/FAST-UAV
License: GPL-3.0-only
Keywords: uav,design,multi-disciplinary
Author: Félix POLLET
Author-email: felix.pollet@isae-supaero.fr
Requires-Python: >=3.8,<3.10
Classifier: Development Status :: 4 - Beta
Classifier: Environment :: Console
Classifier: Intended Audience :: Education
Classifier: Intended Audience :: Science/Research
Classifier: License :: OSI Approved :: GNU General Public License v3 (GPLv3)
Classifier: Natural Language :: English
Classifier: Operating System :: MacOS
Classifier: Operating System :: Microsoft :: Windows
Classifier: Operating System :: POSIX :: Linux
Classifier: Programming Language :: Python :: 3
Classifier: Programming Language :: Python :: 3.8
Classifier: Programming Language :: Python :: 3.9
Classifier: Programming Language :: Python :: 3.7
Classifier: Programming Language :: Python :: 3.8
Classifier: Topic :: Scientific/Engineering :: Physics
Provides-Extra: jupyterlab
Requires-Dist: SALib (==1.4.5)
Requires-Dist: cma (>=3.1.0,<4.0.0)
Requires-Dist: fast-oad-core (>=1.4.1,<2.0.0)
Requires-Dist: kaleido (==0.2.1)
Requires-Dist: matplotlib (>=3.6.2,<4.0.0)
Requires-Dist: numpy (==1.23.1)
Requires-Dist: psutil
Requires-Dist: scikit-learn (>=1.0.2,<2.0.0)
Requires-Dist: stdatm (==0.2.0)
